odoo/addons/announcement_dialog_size/README.rst
odoo/addons/announcement_dialog_size/__init__.py
odoo/addons/announcement_dialog_size/__manifest__.py
odoo/addons/announcement_dialog_size/i18n/announcement_dialog_size.pot
odoo/addons/announcement_dialog_size/i18n/it.po
odoo/addons/announcement_dialog_size/models/__init__.py
odoo/addons/announcement_dialog_size/models/announcement.py
odoo/addons/announcement_dialog_size/readme/CONFIGURE.rst
odoo/addons/announcement_dialog_size/readme/CONTRIBUTORS.rst
odoo/addons/announcement_dialog_size/readme/DESCRIPTION.rst
odoo/addons/announcement_dialog_size/static/description/icon.png
odoo/addons/announcement_dialog_size/static/description/index.html
odoo/addons/announcement_dialog_size/static/src/js/announcement_dialog/announcement_dialog.esm.js
odoo/addons/announcement_dialog_size/static/src/js/announcement_dialog/announcement_dialog.xml
odoo/addons/announcement_dialog_size/static/src/js/announcement_menu/announcement_menu.esm.js
odoo_addon_announcement_dialog_size-16.0.1.0.0.4.dist-info/METADATA
odoo_addon_announcement_dialog_size-16.0.1.0.0.4.dist-info/WHEEL
odoo_addon_announcement_dialog_size-16.0.1.0.0.4.dist-info/top_level.txt
odoo_addon_announcement_dialog_size-16.0.1.0.0.4.dist-info/RECORD
