Metadata-Version: 2.1
Name: odoo-addon-announcement-dialog-size
Version: 16.0.1.0.0.4
Summary: Allow set announcement dialogs fullsized by default
Home-page: https://github.com/OCA/server-ux
Author: Tecnativa, Odoo Community Association (OCA)
Author-email: support@odoo-community.org
License: AGPL-3
Platform: UNKNOWN
Classifier: Programming Language :: Python
Classifier: Framework :: Odoo
Classifier: Framework :: Odoo :: 16.0
Classifier: License :: OSI Approved :: GNU Affero General Public License v3
Requires-Python: >=3.10
Requires-Dist: odoo-addon-announcement <16.1dev,>=16.0dev
Requires-Dist: odoo-addon-web-dialog-size <16.1dev,>=16.0dev
Requires-Dist: odoo <16.1dev,>=16.0a
